[{"name":"bcsstk02.mtx","n":66,"nnz":2211,"results":{"cg_sparse":{"fill":26.4694,"solve":0.848114},"cg_boost_vectors":{"fill":30.993,"solve":1.89745},"cg_vectors":{"fill":32.767,"solve":0.161101}}},{"name":"bcsstk04.mtx","n":132,"nnz":1890,"results":{"cg_sparse":{"fill":19.5066,"solve":5.55737},"cg_boost_vectors":{"fill":21.224,"solve":11.8045},"cg_vectors":{"fill":19.7085,"solve":3.59803}}},{"name":"lund_a.mtx","n":147,"nnz":1298,"results":{"cg_sparse":{"fill":5.76046,"solve":2.32415},"cg_boost_vectors":{"fill":5.95266,"solve":5.81084},"cg_vectors":{"fill":5.53902,"solve":1.12678}}},{"name":"Trefethen_150.mtx","n":150,"nnz":1095,"results":{"cg_sparse":{"fill":2.78693,"solve":0.35548},"cg_boost_vectors":{"fill":5.1428,"solve":2.14967},"cg_vectors":{"fill":2.60157,"solve":2.53905}}},{"name":"bcsstk05.mtx","n":153,"nnz":1288,"results":{"cg_sparse":{"fill":17.7644,"solve":1.86293},"cg_boost_vectors":{"fill":13.674,"solve":4.89244},"cg_vectors":{"fill":13.7213,"solve":3.10322}}},{"name":"Trefethen_200.mtx","n":200,"nnz":1545,"results":{"cg_sparse":{"fill":2.53532,"solve":0.595266},"cg_boost_vectors":{"fill":4.41411,"solve":2.65226},"cg_vectors":{"fill":3.61731,"solve":5.49579}}},{"name":"Trefethen_300.mtx","n":300,"nnz":2489,"results":{"cg_sparse":{"fill":4.1594,"solve":1.2235},"cg_boost_vectors":{"fill":7.47068,"solve":5.20873},"cg_vectors":{"fill":8.92556,"solve":20.694}}},{"name":"mesh2e1.mtx","n":306,"nnz":1162,"results":{"cg_sparse":{"fill":16.1148,"solve":0.702874},"cg_boost_vectors":{"fill":18.8361,"solve":4.30059},"cg_vectors":{"fill":12.6212,"solve":8.81578}}},{"name":"mesh2em5.mtx","n":306,"nnz":1162,"results":{"cg_sparse":{"fill":14.7115,"solve":0.571629},"cg_boost_vectors":{"fill":21.5126,"solve":3.38499},"cg_vectors":{"fill":14.3955,"solve":10.5518}}},{"name":"plat362.mtx","n":362,"nnz":3074,"results":{"cg_sparse":{"fill":41.5958,"solve":144.461},"cg_boost_vectors":{"fill":45.0785,"solve":472.396},"cg_vectors":{"fill":41.0845,"solve":5.15026}}},{"name":"mhdb416.mtx","n":416,"nnz":1364,"results":{"cg_sparse":{"fill":12.6088,"solve":31.935},"cg_boost_vectors":{"fill":15.5469,"solve":162.919},"cg_vectors":{"fill":15.5854,"solve":647.283}}},{"name":"bcsstk06.mtx","n":420,"nnz":4140,"results":{"cg_sparse":{"fill":37.8059,"solve":56.2044},"cg_boost_vectors":{"fill":43.72,"solve":213.805},"cg_vectors":{"fill":41.4363,"solve":77.0064}}},{"name":"bcsstk07.mtx","n":420,"nnz":4140,"results":{"cg_sparse":{"fill":37.414,"solve":57.245},"cg_boost_vectors":{"fill":42.3715,"solve":213.161},"cg_vectors":{"fill":41.6033,"solve":76.3607}}},{"name":"bcsstm07.mtx","n":420,"nnz":3836,"results":{"cg_sparse":{"fill":43.8329,"solve":4.15411},"cg_boost_vectors":{"fill":50.7767,"solve":18.0533},"cg_vectors":{"fill":48.7676,"solve":31.8489}}},{"name":"nos5.mtx","n":468,"nnz":2820,"results":{"cg_sparse":{"fill":9.87507,"solve":4.53758},"cg_boost_vectors":{"fill":14.2649,"solve":20.1843},"cg_vectors":{"fill":12.3939,"solve":10.4287}}},{"name":"bcsstk20.mtx","n":485,"nnz":1810,"results":{"cg_sparse":{"fill":9.75782,"solve":432.63},"cg_boost_vectors":{"fill":12.9263,"solve":2651.21},"cg_vectors":{"fill":12.7394,"solve":762.243}}},{"name":"494_bus.mtx","n":494,"nnz":1080,"results":{"cg_sparse":{"fill":7.60254,"solve":8.05008},"cg_boost_vectors":{"fill":10.7798,"solve":59.6503},"cg_vectors":{"fill":10.3848,"solve":184.175}}},{"name":"Trefethen_500.mtx","n":500,"nnz":4489,"results":{"cg_sparse":{"fill":7.33197,"solve":2.88987},"cg_boost_vectors":{"fill":15.461,"solve":12.2916},"cg_vectors":{"fill":9.9777,"solve":60.3364}}},{"name":"662_bus.mtx","n":662,"nnz":1568,"results":{"cg_sparse":{"fill":11.194,"solve":5.0299},"cg_boost_vectors":{"fill":18.8134,"solve":36.8567},"cg_vectors":{"fill":14.8173,"solve":125.78}}},{"name":"nos6.mtx","n":675,"nnz":1965,"results":{"cg_sparse":{"fill":7.56709,"solve":11.9737},"cg_boost_vectors":{"fill":11.4074,"solve":79.8101},"cg_vectors":{"fill":14.4154,"solve":81.9548}}},{"name":"685_bus.mtx","n":685,"nnz":1967,"results":{"cg_sparse":{"fill":13.3512,"solve":5.41275},"cg_boost_vectors":{"fill":18.7219,"solve":35.0967},"cg_vectors":{"fill":17.2727,"solve":138.211}}},{"name":"nos7.mtx","n":729,"nnz":2673,"results":{"cg_sparse":{"fill":8.22425,"solve":46.2877},"cg_boost_vectors":{"fill":13.066,"solve":271.603},"cg_vectors":{"fill":12.0369,"solve":129.364}}},{"name":"bcsstk19.mtx","n":817,"nnz":3835,"results":{"cg_sparse":{"fill":27.9427,"solve":3987.05},"cg_boost_vectors":{"fill":36.634,"solve":18932.5},"cg_vectors":{"fill":31.5083,"solve":4845.86}}},{"name":"gr_30_30.mtx","n":900,"nnz":4322,"results":{"cg_sparse":{"fill":7.08099,"solve":1.00735},"cg_boost_vectors":{"fill":12.6564,"solve":5.0439},"cg_vectors":{"fill":11.5772,"solve":4.74626}}},{"name":"nos2.mtx","n":957,"nnz":2547,"results":{"cg_sparse":{"fill":5.5922,"solve":660.562},"cg_boost_vectors":{"fill":12.0322,"solve":3972.73},"cg_vectors":{"fill":10.5459,"solve":59.3984}}},{"name":"1138_bus.mtx","n":1138,"nnz":2596,"results":{"cg_sparse":{"fill":17.937,"solve":38.8714},"cg_boost_vectors":{"fill":26.0937,"solve":255.358},"cg_vectors":{"fill":24.3661,"solve":1700.85}}},{"name":"bcsstm26.mtx","n":1922,"nnz":1922,"results":{"cg_sparse":{"fill":22.923,"solve":36.1722},"cg_boost_vectors":{"fill":31.9621,"solve":361.32},"cg_vectors":{"fill":32.7107,"solve":11215.5}}},{"name":"Chem97ZtZ.mtx","n":2541,"nnz":4951,"results":{"cg_sparse":{"fill":27.3465,"solve":2.78319},"cg_boost_vectors":{"fill":50.8815,"solve":21.2949},"cg_vectors":{"fill":40.7919,"solve":957.485}}},{"name":"bcsstm23.mtx","n":3134,"nnz":3134,"results":{"cg_sparse":{"fill":31.5684,"solve":130.915},"cg_boost_vectors":{"fill":48.0193,"solve":1180.91},"cg_vectors":{"fill":48.7284,"solve":69017.1}}},{"name":"bcsstm24.mtx","n":3562,"nnz":3562,"results":{"cg_sparse":{"fill":38.1477,"solve":724.092},"cg_boost_vectors":{"fill":58.6897,"solve":6778.99},"cg_vectors":{"fill":59.0078,"solve":414557}}},{"name":"bcsstm21.mtx","n":3600,"nnz":3600,"results":{"cg_sparse":{"fill":47.0098,"solve":0.216149},"cg_boost_vectors":{"fill":66.9711,"solve":1.47417},"cg_vectors":{"fill":74.2064,"solve":83.8846}}},{"name":"t2dal_e.mtx","n":4257,"nnz":4257,"results":{"cg_sparse":{"fill":89.4195,"solve":792.973},"cg_boost_vectors":{"fill":101.406,"solve":7259.91},"cg_vectors":{"fill":116.044,"solve":367014}}}]